cstrees/__init__.py
cstrees/__main__.py
cstrees/__meta__.py
cstrees/cstree.py
cstrees/dependence.py
cstrees/double_cvar_stagings.py
cstrees/evaluate.py
cstrees/examp_datasets.py
cstrees/ldag.py
cstrees/learning.py
cstrees/scoring.py
cstrees/stage.py
cstrees/datasets/__init__.py
cstrees/datasets/sachs_observational.csv
cstrees/tests/__init__.py
cstrees/tests/__main__.py
cstrees/tests/test_cstrees.py
cstrees/tests/test_documentation.py
cstrees/tests/test_evaluate.py
tests/__init__.py
tests/__meta__.py
tests/test_double_cvar_stagings.py
tests/test_to_minimal_csis.py
cstrees-1.3.1.dist-info/LICENSE
cstrees-1.3.1.dist-info/METADATA
cstrees-1.3.1.dist-info/WHEEL
cstrees-1.3.1.dist-info/top_level.txt
cstrees-1.3.1.dist-info/RECORD
