Metadata-Version: 2.1
Name: cstrees
Version: 1.3.1
Summary: A Python library for CStrees.
Home-page: https://github.com/felixleopoldo/cstrees
Author: Felix Rios
Author-email: felix.leopoldo.rios@gmail.com
Platform: any
Classifier: Development Status :: 3 - Alpha
Classifier: Intended Audience :: Developers
Classifier: License :: OSI Approved :: Apache Software License
Classifier: Operating System :: OS Independent
Classifier: Programming Language :: Python
Classifier: Programming Language :: Python :: 3
Classifier: Programming Language :: Python :: 3.3
Classifier: Programming Language :: Python :: 3.4
Classifier: Programming Language :: Python :: 3.5
Classifier: Topic :: Software Development :: Libraries
License-File: LICENSE
Requires-Dist: numpy <2.0.0
Requires-Dist: networkx
Requires-Dist: pytest
Requires-Dist: manuel
Requires-Dist: pydot
Requires-Dist: matplotlib
Requires-Dist: pygraphviz
Requires-Dist: pandas
Requires-Dist: ipython
Requires-Dist: ipykernel
Requires-Dist: mpl-tools
Requires-Dist: tqdm
Requires-Dist: pp-ez
Requires-Dist: causal-learn
Requires-Dist: pgmpy
Requires-Dist: pylint
Requires-Dist: sphinx
Requires-Dist: seaborn
Provides-Extra: dev
Requires-Dist: python-boilerplate[dev] ; extra == 'dev'
